flex_uuid/__init__.py
flex_uuid/sqlalchemy_type.py
flex_uuid/types.py
flex_uuid_python-0.1.1.dist-info/METADATA
flex_uuid_python-0.1.1.dist-info/WHEEL
flex_uuid_python-0.1.1.dist-info/licenses/LICENSE
flex_uuid_python-0.1.1.dist-info/RECORD
