Metadata-Version: 2.4
Name: flex-uuid-python
Version: 0.1.1
Summary: Flexible UUID parsing, normalization, and SQLAlchemy integration
Project-URL: Homepage, https://github.com/your/repo
Author-email: Dehkartes <dehkartes@gmail.com>
License: MIT
License-File: LICENSE
Classifier: Development Status :: 3 - Alpha
Classifier: Intended Audience :: Developers
Classifier: License :: OSI Approved :: MIT License
Classifier: Programming Language :: Python
Classifier: Programming Language :: Python :: 3
Classifier: Programming Language :: Python :: 3 :: Only
Classifier: Typing :: Typed
Requires-Python: >=3.8
Requires-Dist: build>=1.2.2.post1
Requires-Dist: hypothesis>=6.113.0
Requires-Dist: pytest>=8.3.5
Requires-Dist: sqlalchemy>=2.0
Requires-Dist: twine>=6.1.0
